emu_data_loader/__init__.py
emu_data_loader/loader.py
emu_data_loader-0.2.dist-info/METADATA
emu_data_loader-0.2.dist-info/WHEEL
emu_data_loader-0.2.dist-info/top_level.txt
emu_data_loader-0.2.dist-info/RECORD
